kiipy/__init__.py
kiipy/abi/swap.json
kiipy/aerial/__init__.py
kiipy/aerial/client/__init__.py
kiipy/aerial/client/bank.py
kiipy/aerial/client/distribution.py
kiipy/aerial/client/staking.py
kiipy/aerial/client/utils.py
kiipy/aerial/coins.py
kiipy/aerial/config.py
kiipy/aerial/contract/__init__.py
kiipy/aerial/contract/cosmwasm.py
kiipy/aerial/exceptions.py
kiipy/aerial/faucet.py
kiipy/aerial/gas.py
kiipy/aerial/tx.py
kiipy/aerial/tx_helpers.py
kiipy/aerial/urls.py
kiipy/aerial/wallet.py
kiipy/auth/__init__.py
kiipy/auth/interface.py
kiipy/auth/rest_client.py
kiipy/bank/__init__.py
kiipy/bank/interface.py
kiipy/bank/rest_client.py
kiipy/common/__init__.py
kiipy/common/rest_client.py
kiipy/common/types.py
kiipy/common/utils.py
kiipy/cosmwasm/__init__.py
kiipy/cosmwasm/interface.py
kiipy/cosmwasm/rest_client.py
kiipy/crypto/__init__.py
kiipy/crypto/address.py
kiipy/crypto/hashfuncs.py
kiipy/crypto/interface.py
kiipy/crypto/keypairs.py
kiipy/distribution/__init__.py
kiipy/distribution/interface.py
kiipy/distribution/rest_client.py
kiipy/evidence/__init__.py
kiipy/evidence/interface.py
kiipy/evidence/rest_client.py
kiipy/gov/__init__.py
kiipy/gov/interface.py
kiipy/gov/rest_client.py
kiipy/ibc/__init__.py
kiipy/ibc/applications/transfer/__init__.py
kiipy/ibc/applications/transfer/interface.py
kiipy/ibc/applications/transfer/rest_client.py
kiipy/ibc/core/channel/__init__.py
kiipy/ibc/core/channel/interface.py
kiipy/ibc/core/channel/rest_client.py
kiipy/ibc/core/client/__init__.py
kiipy/ibc/core/client/interface.py
kiipy/ibc/core/client/rest_client.py
kiipy/ibc/core/connection/__init__.py
kiipy/ibc/core/connection/interface.py
kiipy/ibc/core/connection/rest_client.py
kiipy/mint/__init__.py
kiipy/mint/interface.py
kiipy/mint/rest_client.py
kiipy/mnemonic/__init__.py
kiipy/mnemonic/words/__init__.py
kiipy/mnemonic/words/english.py
kiipy/params/__init__.py
kiipy/params/interface.py
kiipy/params/rest_client.py
kiipy/protos/__init__.py
kiipy/protos/amino/__init__.py
kiipy-0.1.0.dist-info/LICENSE
kiipy-0.1.0.dist-info/METADATA
kiipy-0.1.0.dist-info/WHEEL
kiipy-0.1.0.dist-info/RECORD
