Metadata-Version: 2.1
Name: kiipy
Version: 0.1.0
Summary: A Python SDK for Kii
Home-page: https://github.com/KiiBlockchain/kiipy
License: Apache-2.0
Keywords: KiiPy,Cosmos-SDK
Author: Kii Global
Requires-Python: >=3.8,<4.0
Classifier: Development Status :: 3 - Alpha
Classifier: Environment :: Console
Classifier: Intended Audience :: Developers
Classifier: Intended Audience :: Information Technology
Classifier: License :: OSI Approved :: Apache Software License
Classifier: Natural Language :: English
Classifier: Operating System :: MacOS
Classifier: Operating System :: Microsoft :: Windows
Classifier: Operating System :: Unix
Classifier: Programming Language :: Python :: 3
Classifier: Programming Language :: Python :: 3.8
Classifier: Programming Language :: Python :: 3.9
Classifier: Programming Language :: Python :: 3.10
Classifier: Programming Language :: Python :: 3.11
Classifier: Programming Language :: Python :: 3.12
Classifier: Topic :: Software Development
Classifier: Topic :: Software Development :: Libraries :: Python Modules
Classifier: Topic :: System
Requires-Dist: bech32
Requires-Dist: ecdsa
Requires-Dist: googleapis-common-protos
Requires-Dist: grpcio
Requires-Dist: jsonschema (>=3.2.0,<5)
Requires-Dist: prettytable (>=3.10.0,<4.0.0)
Requires-Dist: protobuf (>=4.21.6,<5.0dev)
Requires-Dist: pycryptodome (>=3.18.0,<4.0.0)
Requires-Dist: python-dateutil
Requires-Dist: requests
Project-URL: Repository, https://github.com/KiiBlockchain/kiipy
